memocache/__init__.py
memocache/evictor.py
memocache/file_manager.py
memocache/memo.py
memocache/serializer.py
memocache/strategies.py
memocache/sync.py
memocache-0.0.3.dist-info/LICENSE
memocache-0.0.3.dist-info/METADATA
memocache-0.0.3.dist-info/WHEEL
memocache-0.0.3.dist-info/top_level.txt
memocache-0.0.3.dist-info/RECORD
