Metadata-Version: 2.1
Name: memocache
Version: 0.0.3
Summary: A decorator that optimizes function execution by caching results. With support for different eviction strategies (LFU, LRU, FIFO).
Home-page: https://github.com/BrunoCiccarino/standlib
Author: BrunoCiccarino
Author-email: ciccabr9@gmail.com
Classifier: Programming Language :: Python :: 3
Classifier: License :: OSI Approved :: MIT License
Classifier: Operating System :: OS Independent
Requires-Python: >=3.6
License-File: LICENSE
